pulumi_harness/__init__.py
pulumi_harness/_inputs.py
pulumi_harness/_utilities.py
pulumi_harness/add_user_to_group.py
pulumi_harness/application.py
pulumi_harness/application_git_sync.py
pulumi_harness/chaos_infrastructure.py
pulumi_harness/delegate_approval.py
pulumi_harness/encrypted_text.py
pulumi_harness/environment.py
pulumi_harness/get_application.py
pulumi_harness/get_chaos_infrastructure.py
pulumi_harness/get_current_account.py
pulumi_harness/get_delegate.py
pulumi_harness/get_encrypted_text.py
pulumi_harness/get_environment.py
pulumi_harness/get_git_connector.py
pulumi_harness/get_secret_manager.py
pulumi_harness/get_service.py
pulumi_harness/get_ssh_credential.py
pulumi_harness/get_sso_provider.py
pulumi_harness/get_trigger.py
pulumi_harness/get_user.py
pulumi_harness/get_user_group.py
pulumi_harness/get_yaml_config.py
pulumi_harness/git_connector.py
pulumi_harness/infrastructure_definition.py
pulumi_harness/outputs.py
pulumi_harness/platform_api_key.py
pulumi_harness/platform_ccm_filters.py
pulumi_harness/provider.py
pulumi_harness/pulumi-plugin.json
pulumi_harness/py.typed
pulumi_harness/ssh_credential.py
pulumi_harness/user.py
pulumi_harness/user_group.py
pulumi_harness/user_group_permissions.py
pulumi_harness/yaml_config.py
pulumi_harness/autostopping/__init__.py
pulumi_harness/autostopping/_inputs.py
pulumi_harness/autostopping/aws_alb.py
pulumi_harness/autostopping/aws_proxy.py
pulumi_harness/autostopping/azure_gateway.py
pulumi_harness/autostopping/azure_proxy.py
pulumi_harness/autostopping/gcp_proxy.py
pulumi_harness/autostopping/get_aws_alb.py
pulumi_harness/autostopping/get_aws_proxy.py
pulumi_harness/autostopping/get_azure_gateway.py
pulumi_harness/autostopping/get_azure_proxy.py
pulumi_harness/autostopping/get_gcp_proxy.py
pulumi_harness/autostopping/get_rule_ecs.py
pulumi_harness/autostopping/get_rule_rds.py
pulumi_harness/autostopping/get_rule_scale_group.py
pulumi_harness/autostopping/get_rule_vm.py
pulumi_harness-0.11.0.dist-info/METADATA
pulumi_harness-0.11.0.dist-info/WHEEL
pulumi_harness-0.11.0.dist-info/top_level.txt
pulumi_harness-0.11.0.dist-info/RECORD
